<?xml version="1.0" encoding="utf-8"?><datamap>
	<asciibinary>
		
		<item><ascii> </ascii><binary>00100000</binary></item>
		<item><ascii>!</ascii><binary>00100001</binary></item>
		<item><ascii>"</ascii><binary>00100010</binary></item>
		<item><ascii>#</ascii><binary>00100011</binary></item>
		<item><ascii>$</ascii><binary>00100100</binary></item>
		<item><ascii>%</ascii><binary>00100101</binary></item>
		<item><ascii>&amp;</ascii><binary>00100110</binary></item>
		<item><ascii>'</ascii><binary>00100111</binary></item>
		<item><ascii>(</ascii><binary>00101000</binary></item>
		<item><ascii>)</ascii><binary>00101001</binary></item>
		<item><ascii>*</ascii><binary>00101010</binary></item>
		<item><ascii>+</ascii><binary>00101011</binary></item>
		<item><ascii>,</ascii><binary>00101100</binary></item>
		<item><ascii>-</ascii><binary>00101101</binary></item>
		<item><ascii>.</ascii><binary>00101110</binary></item>
		<item><ascii>/</ascii><binary>00101111</binary></item>
		<item><ascii>0</ascii><binary>00110000</binary></item>
		<item><ascii>1</ascii><binary>00110001</binary></item>
		<item><ascii>2</ascii><binary>00110010</binary></item>
		<item><ascii>3</ascii><binary>00110011</binary></item>
		<item><ascii>4</ascii><binary>00110100</binary></item>
		<item><ascii>5</ascii><binary>00110101</binary></item>
		<item><ascii>6</ascii><binary>00110110</binary></item>
		<item><ascii>7</ascii><binary>00110111</binary></item>
		<item><ascii>8</ascii><binary>00111000</binary></item>
		<item><ascii>9</ascii><binary>00111001</binary></item>
		<item><ascii>:</ascii><binary>00111010</binary></item>
		<item><ascii>;</ascii><binary>00111011</binary></item>
		<item><ascii>&lt;</ascii><binary>00111100</binary></item>
		<item><ascii>=</ascii><binary>00111101</binary></item>
		<item><ascii>&gt;</ascii><binary>00111110</binary></item>
		<item><ascii>?</ascii><binary>00111111</binary></item>
		<item><ascii>@</ascii><binary>01000000</binary></item>
		<item><ascii>A</ascii><binary>01000001</binary></item>
		<item><ascii>B</ascii><binary>01000010</binary></item>
		<item><ascii>C</ascii><binary>01000011</binary></item>
		<item><ascii>D</ascii><binary>01000100</binary></item>
		<item><ascii>E</ascii><binary>01000101</binary></item>
		<item><ascii>F</ascii><binary>01000110</binary></item>
		<item><ascii>G</ascii><binary>01000111</binary></item>
		<item><ascii>H</ascii><binary>01001000</binary></item>
		<item><ascii>I</ascii><binary>01001001</binary></item>
		<item><ascii>J</ascii><binary>01001010</binary></item>
		<item><ascii>K</ascii><binary>01001011</binary></item>
		<item><ascii>L</ascii><binary>01001100</binary></item>
		<item><ascii>M</ascii><binary>01001101</binary></item>
		<item><ascii>N</ascii><binary>01001110</binary></item>
		<item><ascii>O</ascii><binary>01001111</binary></item>
		<item><ascii>P</ascii><binary>01010000</binary></item>
		<item><ascii>Q</ascii><binary>01010001</binary></item>
		<item><ascii>R</ascii><binary>01010010</binary></item>
		<item><ascii>S</ascii><binary>01010011</binary></item>
		<item><ascii>T</ascii><binary>01010100</binary></item>
		<item><ascii>U</ascii><binary>01010101</binary></item>
		<item><ascii>V</ascii><binary>01010110</binary></item>
		<item><ascii>W</ascii><binary>01010111</binary></item>
		<item><ascii>X</ascii><binary>01011000</binary></item>
		<item><ascii>Y</ascii><binary>01011001</binary></item>
		<item><ascii>Z</ascii><binary>01011010</binary></item>
		<item><ascii>[</ascii><binary>01011011</binary></item>
		<item><ascii>\</ascii><binary>01011100</binary></item>
		<item><ascii>]</ascii><binary>01011101</binary></item>
		<item><ascii>^</ascii><binary>01011110</binary></item>
		<item><ascii>_</ascii><binary>01011111</binary></item>
		<item><ascii>`</ascii><binary>01100000</binary></item>
		<item><ascii>a</ascii><binary>01100001</binary></item>
		<item><ascii>b</ascii><binary>01100010</binary></item>
		<item><ascii>c</ascii><binary>01100011</binary></item>
		<item><ascii>d</ascii><binary>01100100</binary></item>
		<item><ascii>e</ascii><binary>01100101</binary></item>
		<item><ascii>f</ascii><binary>01100110</binary></item>
		<item><ascii>g</ascii><binary>01100111</binary></item>
		<item><ascii>h</ascii><binary>01101000</binary></item>
		<item><ascii>i</ascii><binary>01101001</binary></item>
		<item><ascii>j</ascii><binary>01101010</binary></item>
		<item><ascii>k</ascii><binary>01101011</binary></item>
		<item><ascii>l</ascii><binary>01101100</binary></item>
		<item><ascii>m</ascii><binary>01101101</binary></item>
		<item><ascii>n</ascii><binary>01101110</binary></item>
		<item><ascii>o</ascii><binary>01101111</binary></item>
		<item><ascii>p</ascii><binary>01110000</binary></item>
		<item><ascii>q</ascii><binary>01110001</binary></item>
		<item><ascii>r</ascii><binary>01110010</binary></item>
		<item><ascii>s</ascii><binary>01110011</binary></item>
		<item><ascii>t</ascii><binary>01110100</binary></item>
		<item><ascii>u</ascii><binary>01110101</binary></item>
		<item><ascii>v</ascii><binary>01110110</binary></item>
		<item><ascii>w</ascii><binary>01110111</binary></item>
		<item><ascii>x</ascii><binary>01111000</binary></item>
		<item><ascii>y</ascii><binary>01111001</binary></item>
		<item><ascii>z</ascii><binary>01111010</binary></item>
		<item><ascii>{</ascii><binary>01111011</binary></item>
		<item><ascii>|</ascii><binary>01111100</binary></item>
		<item><ascii>}</ascii><binary>01111101</binary></item>
		<item><ascii>~</ascii><binary>01111110</binary></item>
		<item><ascii>А</ascii><binary>1101000010010000</binary></item>
		<item><ascii>Б</ascii><binary>1101000010010000</binary></item>
		<item><ascii>В</ascii><binary>1101000010010010</binary></item>
		<item><ascii>Г</ascii><binary>1101000010010011</binary></item>
		<item><ascii>Д</ascii><binary>1101000010010100</binary></item>
		<item><ascii>Е</ascii><binary>1101000010010101</binary></item>
		<item><ascii>Ж</ascii><binary>1101000010010110</binary></item>
		<item><ascii>З</ascii><binary>1101000010010111</binary></item>
		<item><ascii>И</ascii><binary>1101000010011000</binary></item>
		<item><ascii>Й</ascii><binary>1101000010011001</binary></item>
		<item><ascii>К</ascii><binary>1101000010011010</binary></item>
		<item><ascii>Л</ascii><binary>1101000010011011</binary></item>
		<item><ascii>М</ascii><binary>1101000010011100</binary></item>
		<item><ascii>Н</ascii><binary>1101000010011101</binary></item>
		<item><ascii>О</ascii><binary>1101000010011110</binary></item>
		<item><ascii>П</ascii><binary>1101000010011111</binary></item>
		<item><ascii>Р</ascii><binary>1101000010100000</binary></item>
		<item><ascii>С</ascii><binary>1101000010100001</binary></item>
		<item><ascii>Т</ascii><binary>1101000010100010</binary></item>
		<item><ascii>У</ascii><binary>1101000010100011</binary></item>
		<item><ascii>Ф</ascii><binary>1101000010100100</binary></item>
		<item><ascii>Х</ascii><binary>1101000010100101</binary></item>
		<item><ascii>Ц</ascii><binary>1101000010100110</binary></item>
		<item><ascii>Ч</ascii><binary>1101000010100111</binary></item>
		<item><ascii>Ш</ascii><binary>1101000010101000</binary></item>
		<item><ascii>Щ</ascii><binary>1101000010101001</binary></item>
		<item><ascii>Ъ</ascii><binary>1101000010101010</binary></item>
		<item><ascii>Ы</ascii><binary>1101000010101011</binary></item>
		<item><ascii>Ь</ascii><binary>1101000010101100</binary></item>
		<item><ascii>Э</ascii><binary>1101000010101101</binary></item>
		<item><ascii>Ю</ascii><binary>1101000010101110</binary></item>
		<item><ascii>Я</ascii><binary>1101000010101111</binary></item>
		<item><ascii>а</ascii><binary>1101000010110000</binary></item>
		<item><ascii>б</ascii><binary>1101000010110001</binary></item>
		<item><ascii>в</ascii><binary>1101000010110010</binary></item>
		<item><ascii>г</ascii><binary>1101000010110011</binary></item>
		<item><ascii>д</ascii><binary>1101000010110100</binary></item>
		<item><ascii>е</ascii><binary>1101000010110101</binary></item>
		<item><ascii>ж</ascii><binary>1101000010110110</binary></item>
		<item><ascii>з</ascii><binary>1101000010110111</binary></item>
		<item><ascii>и</ascii><binary>1101000010111000</binary></item>
		<item><ascii>й</ascii><binary>1101000010111001</binary></item>
		<item><ascii>к</ascii><binary>1101000010111010</binary></item>
		<item><ascii>л</ascii><binary>1101000010111011</binary></item>
		<item><ascii>м</ascii><binary>1101000010111100</binary></item>
		<item><ascii>н</ascii><binary>1101000010111101</binary></item>
		<item><ascii>о</ascii><binary>1101000010111110</binary></item>
		<item><ascii>п</ascii><binary>1101000010111111</binary></item>
		<item><ascii>р</ascii><binary>1101000110000000</binary></item>
		<item><ascii>с</ascii><binary>1101000110000001</binary></item>
		<item><ascii>т</ascii><binary>1101000110000010</binary></item>
		<item><ascii>у</ascii><binary>1101000110000011</binary></item>
		<item><ascii>ф</ascii><binary>1101000110000100</binary></item>
		<item><ascii>х</ascii><binary>1101000110000101</binary></item>
		<item><ascii>ц</ascii><binary>1101000110000110</binary></item>
		<item><ascii>ч</ascii><binary>1101000110000111</binary></item>
		<item><ascii>ш</ascii><binary>1101000110001000</binary></item>
		<item><ascii>щ</ascii><binary>1101000110001001</binary></item>
		<item><ascii>ъ</ascii><binary>1101000110001010</binary></item>
		<item><ascii>ы</ascii><binary>1101000110001011</binary></item>
		<item><ascii>ь</ascii><binary>1101000110001100</binary></item>
		<item><ascii>э</ascii><binary>1101000110001101</binary></item>
		<item><ascii>ю</ascii><binary>1101000110001110</binary></item>
		<item><ascii>я</ascii><binary>1101000110001111</binary></item>
	</asciibinary>

	<binarybase64>
		<item><binary>000000</binary><base64>A</base64></item>
		<item><binary>000001</binary><base64>B</base64></item>
		<item><binary>000010</binary><base64>C</base64></item>
		<item><binary>000011</binary><base64>D</base64></item>
		<item><binary>000100</binary><base64>E</base64></item>
		<item><binary>000101</binary><base64>F</base64></item>
		<item><binary>000110</binary><base64>G</base64></item>
		<item><binary>000111</binary><base64>H</base64></item>
		<item><binary>001000</binary><base64>I</base64></item>
		<item><binary>001001</binary><base64>J</base64></item>
		<item><binary>001010</binary><base64>K</base64></item>
		<item><binary>001011</binary><base64>L</base64></item>
		<item><binary>001100</binary><base64>M</base64></item>
		<item><binary>001101</binary><base64>N</base64></item>
		<item><binary>001110</binary><base64>O</base64></item>
		<item><binary>001111</binary><base64>P</base64></item>
		<item><binary>010000</binary><base64>Q</base64></item>
		<item><binary>010001</binary><base64>R</base64></item>
		<item><binary>010010</binary><base64>S</base64></item>
		<item><binary>010011</binary><base64>T</base64></item>
		<item><binary>010100</binary><base64>U</base64></item>
		<item><binary>010101</binary><base64>V</base64></item>
		<item><binary>010110</binary><base64>W</base64></item>
		<item><binary>010111</binary><base64>X</base64></item>
		<item><binary>011000</binary><base64>Y</base64></item>
		<item><binary>011001</binary><base64>Z</base64></item>
		<item><binary>011010</binary><base64>a</base64></item>
		<item><binary>011011</binary><base64>b</base64></item>
		<item><binary>011100</binary><base64>c</base64></item>
		<item><binary>011101</binary><base64>d</base64></item>
		<item><binary>011110</binary><base64>e</base64></item>
		<item><binary>011111</binary><base64>f</base64></item>
		<item><binary>100000</binary><base64>g</base64></item>
		<item><binary>100001</binary><base64>h</base64></item>
		<item><binary>100010</binary><base64>i</base64></item>
		<item><binary>100011</binary><base64>j</base64></item>
		<item><binary>100100</binary><base64>k</base64></item>
		<item><binary>100101</binary><base64>l</base64></item>
		<item><binary>100110</binary><base64>m</base64></item>
		<item><binary>100111</binary><base64>n</base64></item>
		<item><binary>101000</binary><base64>o</base64></item>
		<item><binary>101001</binary><base64>p</base64></item>
		<item><binary>101010</binary><base64>q</base64></item>
		<item><binary>101011</binary><base64>r</base64></item>
		<item><binary>101100</binary><base64>s</base64></item>
		<item><binary>101101</binary><base64>t</base64></item>
		<item><binary>101110</binary><base64>u</base64></item>
		<item><binary>101111</binary><base64>v</base64></item>
		<item><binary>110000</binary><base64>w</base64></item>
		<item><binary>110001</binary><base64>x</base64></item>
		<item><binary>110010</binary><base64>y</base64></item>
		<item><binary>110011</binary><base64>z</base64></item>
		<item><binary>110100</binary><base64>0</base64></item>
		<item><binary>110101</binary><base64>1</base64></item>
		<item><binary>110110</binary><base64>2</base64></item>
		<item><binary>110111</binary><base64>3</base64></item>
		<item><binary>111000</binary><base64>4</base64></item>
		<item><binary>111001</binary><base64>5</base64></item>
		<item><binary>111010</binary><base64>6</base64></item>
		<item><binary>111011</binary><base64>7</base64></item>
		<item><binary>111100</binary><base64>8</base64></item>
		<item><binary>111101</binary><base64>9</base64></item>
		<item><binary>111110</binary><base64>+</base64></item>
		<item><binary>111111</binary><base64>/</base64></item>
		
	</binarybase64>

</datamap>
